nnterp/__init__.py
nnterp/__main__.py
nnterp/display.py
nnterp/interventions.py
nnterp/nnsight_utils.py
nnterp/prompt_utils.py
nnterp/rename_utils.py
nnterp/standardized_transformer.py
nnterp/utils.py
nnterp/tests/__init__.py
nnterp/tests/conftest.py
nnterp/tests/test_config.yaml
nnterp/tests/test_interventions.py
nnterp/tests/test_model_renaming.py
nnterp/tests/test_nnsight_utils.py
nnterp/tests/test_probabilities.py
nnterp/tests/test_prompt_utils.py
nnterp/tests/utils.py
nnterp-1.2.1.dist-info/licenses/LICENSE
nnterp-1.2.1.dist-info/METADATA
nnterp-1.2.1.dist-info/WHEEL
nnterp-1.2.1.dist-info/top_level.txt
nnterp-1.2.1.dist-info/RECORD
