Metadata-Version: 2.4
Name: nnterp
Version: 1.2.1
Summary: Utils and mechanistic interpretability intervensions using nnsight
Author-email: Clément Dumas <butanium.contact@gmail.com>
License: MIT
Project-URL: Homepage, https://github.com/butanium/nnterp
Classifier: Programming Language :: Python :: 3
Classifier: Operating System :: OS Independent
Requires-Python: >=3.9
License-File: LICENSE
Requires-Dist: loguru>=0.7.3
Requires-Dist: nnsight>=0.5
Requires-Dist: transformers
Provides-Extra: display
Requires-Dist: plotly; extra == "display"
Requires-Dist: pandas; extra == "display"
Provides-Extra: llms
Requires-Dist: pillow; extra == "llms"
Requires-Dist: timm; extra == "llms"
Requires-Dist: flash-attn; sys_platform != "win32" and extra == "llms"
Requires-Dist: hf_xet; extra == "llms"
Requires-Dist: sentencepiece; extra == "llms"
Provides-Extra: vllm
Requires-Dist: vllm; extra == "vllm"
Dynamic: license-file
